drf_restflow-1.0.0a2.dist-info/licenses/LICENSE
restflow/__init__.py
restflow/filters/__init__.py
restflow/filters/fields.py
restflow/filters/filters.py
drf_restflow-1.0.0a2.dist-info/METADATA
drf_restflow-1.0.0a2.dist-info/WHEEL
drf_restflow-1.0.0a2.dist-info/top_level.txt
drf_restflow-1.0.0a2.dist-info/RECORD
