Metadata-Version: 2.4
Name: drf-restflow
Version: 1.0.0a2
Summary: A Declarative library for Django REST Framework
Author-email: Khan Asfi Reza <mail@khanasfireza.dev>
License-Expression: BSD-3-Clause
Project-URL: Homepage, https://github.com/khan-asfi-reza/drf-restflow
Project-URL: Repository, https://github.com/khan-asfi-reza/drf-restflow
Project-URL: Issues, https://github.com/khan-asfi-reza/drf-restflow/issues
Project-URL: Changelog, https://github.com/khan-asfi-reza/drf-restflow/releases
Keywords: django,django-rest-framework,drf,filters,queryset,declarative,type-safe,fastapi,rest-api
Classifier: Development Status :: 3 - Alpha
Classifier: Environment :: Web Environment
Classifier: Framework :: Django
Classifier: Framework :: Django :: 3.2
Classifier: Framework :: Django :: 4.0
Classifier: Framework :: Django :: 4.1
Classifier: Framework :: Django :: 4.2
Classifier: Framework :: Django :: 5.0
Classifier: Intended Audience :: Developers
Classifier: Operating System :: OS Independent
Classifier: Programming Language :: Python
Classifier: Programming Language :: Python :: 3
Classifier: Programming Language :: Python :: 3.10
Classifier: Programming Language :: Python :: 3.11
Classifier: Programming Language :: Python :: 3.12
Classifier: Programming Language :: Python :: 3.13
Classifier: Programming Language :: Python :: 3.14
Classifier: Topic :: Internet :: WWW/HTTP
Classifier: Topic :: Software Development :: Libraries :: Python Modules
Classifier: Typing :: Typed
Requires-Python: >=3.10
License-File: LICENSE
Requires-Dist: django>=3.2
Requires-Dist: djangorestframework>=3.14
Dynamic: license-file
